LICENCE
README.md
setup.py
models/__init__.py
models/vae.py
models/w2v.py
models/wgan_gp.py
models/bert/__init__.py
models/bert/simple_BERT.py
models/bert/vanilla_BERT.py
thunet/__init__.py
thunet.egg-info/PKG-INFO
thunet.egg-info/SOURCES.txt
thunet.egg-info/dependency_links.txt
thunet.egg-info/requires.txt
thunet.egg-info/top_level.txt
thunet/neural_nets/__init__.py
thunet/neural_nets/activations/__init__.py
thunet/neural_nets/activations/activations.py
thunet/neural_nets/initializers/__init__.py
thunet/neural_nets/initializers/initializers.py
thunet/neural_nets/layers/__init__.py
thunet/neural_nets/layers/layers.py
thunet/neural_nets/losses/__init__.py
thunet/neural_nets/losses/losses.py
thunet/neural_nets/modules/__init__.py
thunet/neural_nets/modules/modules.py
thunet/neural_nets/optimizers/__init__.py
thunet/neural_nets/optimizers/optimizers.py
thunet/neural_nets/preprocessing/__init__.py
thunet/neural_nets/preprocessing/dsp.py
thunet/neural_nets/preprocessing/general.py
thunet/neural_nets/preprocessing/nlp.py
thunet/neural_nets/schedulers/__init__.py
thunet/neural_nets/schedulers/schedulers.py
thunet/neural_nets/utils/__init__.py
thunet/neural_nets/utils/data_structures.py
thunet/neural_nets/utils/disks.py
thunet/neural_nets/utils/distance_metrics.py
thunet/neural_nets/utils/testing.py
thunet/neural_nets/utils/utils.py
thunet/neural_nets/utils/windows.py
thunet/neural_nets/weights/__init__.py
thunet/neural_nets/weights/weights.py
thunet/neural_nets/wrappers/__init__.py
thunet/neural_nets/wrappers/wrappers.py