Metadata-Version: 2.1
Name: thunet
Version: 0.0.10.202209
Summary: A Deep learning framework for scientific and educational purpose
Home-page: https://github.com/ShenDezhou/thunet
Author: Dezhou Shen
Author-email: sdz15@tsinghua.org.cn
License: GPLv3+
Project-URL: Bug Tracker, https://github.com/ShenDezhou/thunet/issues
Project-URL: Documentation, https://thunet.readthedocs.io/en/latest/
Project-URL: Source, https://github.com/ShenDezhou/thunet
Platform: UNKNOWN
Classifier: Development Status :: 3 - Alpha
Classifier: Intended Audience :: Science/Research
Classifier: Intended Audience :: Developers
Classifier: Topic :: Scientific/Engineering
Classifier: License :: OSI Approved :: GNU Lesser General Public License v3 or later (LGPLv3+)
Classifier: Operating System :: OS Independent
Classifier: Programming Language :: Python :: 2
Classifier: Programming Language :: Python :: 3
Requires-Python: >=2.7, >=3.5
License-File: LICENCE
